{
  "main": {
    "id": "c112b0800deb7243",
    "type": "split",
    "children": [
      {
        "id": "28cd7a5a652b1e87",
        "type": "tabs",
        "children": [
          {
            "id": "64eddf1f99e94532",
            "type": "leaf",
            "state": {
              "type": "markdown",
              "state": {
                "file": "00 Inbox/Obsidian Community Plugins.md",
                "mode": "source",
                "source": false
              },
              "icon": "lucide-file",
              "title": "Obsidian Community Plugins"
            }
          },
          {
            "id": "19920ff0e86f11ae",
            "type": "leaf",
            "state": {
              "type": "markdown",
              "state": {
                "file": "00 Inbox/All Properties Dashboard.md",
                "mode": "source",
                "source": false
              },
              "icon": "lucide-file",
              "title": "All Properties Dashboard"
            }
          },
          {
            "id": "23a8f9c603f85d8e",
            "type": "leaf",
            "state": {
              "type": "markdown",
              "state": {
                "file": "10 Journal/Daily/26_01/02/26-01-02 Daily Notes.md",
                "mode": "source",
                "source": false
              },
              "icon": "lucide-file",
              "title": "26-01-02 Daily Notes"
            }
          },
          {
            "id": "03d28e01391356b2",
            "type": "leaf",
            "state": {
              "type": "markdown",
              "state": {
                "file": "10 Journal/Daily/26_01/02/26-01-02 Daily Notes.md",
                "mode": "source",
                "source": false
              },
              "icon": "lucide-file",
              "title": "26-01-02 Daily Notes"
            }
          },
          {
            "id": "d9f5cd22b8f053fd",
            "type": "leaf",
            "state": {
              "type": "markdown",
              "state": {
                "file": "10 Journal/Daily/26_01/02/26-01-02 Daily Notes.md",
                "mode": "source",
                "source": false
              },
              "icon": "lucide-file",
              "title": "26-01-02 Daily Notes"
            }
          },
          {
            "id": "bfcda00623fdc2d8",
            "type": "leaf",
            "state": {
              "type": "canvas",
              "state": {
                "file": "Uni Map Canvas.canvas",
                "viewState": {
                  "x": 0,
                  "y": 0,
                  "zoom": 0
                }
              },
              "icon": "lucide-layout-dashboard",
              "title": "Uni Map Canvas"
            }
          },
          {
            "id": "c386199b3d1248f2",
            "type": "leaf",
            "state": {
              "type": "canvas",
              "state": {
                "file": "Uni Map Canvas.canvas",
                "viewState": {
                  "x": 0,
                  "y": 0,
                  "zoom": 0
                }
              },
              "icon": "lucide-layout-dashboard",
              "title": "Uni Map Canvas"
            }
          },
          {
            "id": "1d1bc82e321200fe",
            "type": "leaf",
            "state": {
              "type": "canvas",
              "state": {
                "file": "Uni Map Canvas.canvas",
                "viewState": {
                  "x": 0,
                  "y": 223.20000000000002,
                  "zoom": 0
                }
              },
              "icon": "lucide-layout-dashboard",
              "title": "Uni Map Canvas"
            }
          },
          {
            "id": "bb5c0670993817f4",
            "type": "leaf",
            "state": {
              "type": "canvas",
              "state": {
                "file": "Uni Map Canvas.canvas",
                "viewState": {
                  "x": 68.5,
                  "y": -73,
                  "zoom": 0
                }
              },
              "icon": "lucide-layout-dashboard",
              "title": "Uni Map Canvas"
            }
          },
          {
            "id": "118b313439429941",
            "type": "leaf",
            "state": {
              "type": "canvas",
              "state": {
                "file": "Uni Map Canvas.canvas",
                "viewState": {
                  "x": 68.5,
                  "y": -220,
                  "zoom": 0
                }
              },
              "icon": "lucide-layout-dashboard",
              "title": "Uni Map Canvas"
            }
          },
          {
            "id": "2d958948b69c5f25",
            "type": "leaf",
            "state": {
              "type": "canvas",
              "state": {
                "file": "Uni Map Canvas.canvas",
                "viewState": {
                  "x": 183,
                  "y": -764.5,
                  "zoom": 0
                }
              },
              "icon": "lucide-layout-dashboard",
              "title": "Uni Map Canvas"
            }
          },
          {
            "id": "6df8c5abb0088a57",
            "type": "leaf",
            "state": {
              "type": "canvas",
              "state": {
                "file": "Uni Map Canvas.canvas",
                "viewState": {
                  "x": 16,
                  "y": -640.5,
                  "zoom": 0
                }
              },
              "icon": "lucide-layout-dashboard",
              "title": "Uni Map Canvas"
            }
          },
          {
            "id": "44df9f7ac0b50f22",
            "type": "leaf",
            "state": {
              "type": "canvas",
              "state": {
                "file": "Uni Map Canvas.canvas",
                "viewState": {
                  "x": 300,
                  "y": -540,
                  "zoom": -0.28647813003535416
                }
              },
              "icon": "lucide-layout-dashboard",
              "title": "Uni Map Canvas"
            }
          },
          {
            "id": "d7b29a8d5d5ac211",
            "type": "leaf",
            "state": {
              "type": "canvas",
              "state": {
                "file": "Uni Map Canvas.canvas",
                "viewState": {
                  "x": 300,
                  "y": -540,
                  "zoom": -0.28647813003535416
                }
              },
              "icon": "lucide-layout-dashboard",
              "title": "Uni Map Canvas"
            }
          },
          {
            "id": "fb77138dc372fb58",
            "type": "leaf",
            "state": {
              "type": "canvas",
              "state": {
                "file": "Uni Map Canvas.canvas",
                "viewState": {
                  "x": 300,
                  "y": -812.2279423328964,
                  "zoom": -0.28647813003535416
                }
              },
              "icon": "lucide-layout-dashboard",
              "title": "Uni Map Canvas"
            }
          },
          {
            "id": "6f6a4280e16cda64",
            "type": "leaf",
            "state": {
              "type": "markdown",
              "state": {
                "file": "40 Knowledge/Scrum/Why We Replaced Daily Standups with Written Daily Logs.md",
                "mode": "source",
                "source": false
              },
              "icon": "lucide-file",
              "title": "Why We Replaced Daily Standups with Written Daily Logs"
            }
          },
          {
            "id": "990268ca7030a666",
            "type": "leaf",
            "state": {
              "type": "markdown",
              "state": {
                "file": "80 Back Office/Cosmos for Books.md",
                "mode": "source",
                "source": false
              },
              "icon": "lucide-file",
              "title": "Cosmos for Books"
            }
          },
          {
            "id": "79a9cbe0c1063bcb",
            "type": "leaf",
            "state": {
              "type": "markdown",
              "state": {
                "file": "40 Knowledge/10 Books/2024/2024 - Transformed by Marty Cagan.md",
                "mode": "source",
                "source": false
              },
              "icon": "lucide-file",
              "title": "2024 - Transformed by Marty Cagan"
            }
          },
          {
            "id": "71755b7072f28914",
            "type": "leaf",
            "state": {
              "type": "canvas",
              "state": {
                "file": "Uni Map Canvas.canvas",
                "viewState": {
                  "x": -33.024818433859906,
                  "y": -728.6093159820301,
                  "zoom": 0.1720250173261867
                }
              },
              "icon": "lucide-layout-dashboard",
              "title": "Uni Map Canvas"
            }
          }
        ],
        "currentTab": 17
      }
    ],
    "direction": "vertical"
  },
  "left": {
    "id": "237c54f104f5e6d0",
    "type": "split",
    "children": [
      {
        "id": "cc3009fd51799d36",
        "type": "tabs",
        "children": [
          {
            "id": "01bde706ddefb4c5",
            "type": "leaf",
            "state": {
              "type": "file-explorer",
              "state": {
                "sortOrder": "alphabetical",
                "autoReveal": true
              },
              "icon": "lucide-folder-closed",
              "title": "Files"
            }
          },
          {
            "id": "43cdae9f953a9715",
            "type": "leaf",
            "state": {
              "type": "search",
              "state": {
                "query": "plugin",
                "matchingCase": false,
                "explainSearch": false,
                "collapseAll": false,
                "extraContext": false,
                "sortOrder": "alphabetical"
              },
              "icon": "lucide-search",
              "title": "Search"
            }
          },
          {
            "id": "3f15a5694994cca4",
            "type": "leaf",
            "state": {
              "type": "bookmarks",
              "state": {},
              "icon": "lucide-bookmark",
              "title": "Bookmarks"
            }
          }
        ]
      }
    ],
    "direction": "horizontal",
    "width": 300
  },
  "right": {
    "id": "245e0a3393519020",
    "type": "split",
    "children": [
      {
        "id": "b672b6ef61f5f609",
        "type": "tabs",
        "children": [
          {
            "id": "a9f7d8caffe17423",
            "type": "leaf",
            "state": {
              "type": "backlink",
              "state": {
                "file": "Obsidian Community Plugins.md",
                "collapseAll": false,
                "extraContext": false,
                "sortOrder": "alphabetical",
                "showSearch": false,
                "searchQuery": "",
                "backlinkCollapsed": false,
                "unlinkedCollapsed": true
              },
              "icon": "links-coming-in",
              "title": "Backlinks for Obsidian Community Plugins"
            }
          },
          {
            "id": "4a17f9bdbae7aea2",
            "type": "leaf",
            "state": {
              "type": "outgoing-link",
              "state": {
                "file": "Obsidian Community Plugins.md",
                "linksCollapsed": false,
                "unlinkedCollapsed": true
              },
              "icon": "links-going-out",
              "title": "Outgoing links from Obsidian Community Plugins"
            }
          },
          {
            "id": "88c72e0482c77e71",
            "type": "leaf",
            "state": {
              "type": "tag",
              "state": {
                "sortOrder": "frequency",
                "useHierarchy": true,
                "showSearch": false,
                "searchQuery": ""
              },
              "icon": "lucide-tags",
              "title": "Tags"
            }
          },
          {
            "id": "2b370f03aafd4d56",
            "type": "leaf",
            "state": {
              "type": "all-properties",
              "state": {
                "sortOrder": "frequency",
                "showSearch": false,
                "searchQuery": ""
              },
              "icon": "lucide-archive",
              "title": "All properties"
            }
          },
          {
            "id": "7bca492d0cc20729",
            "type": "leaf",
            "state": {
              "type": "outline",
              "state": {
                "file": "40 Knowledge/10 Books/2024/2024 - Transformed by Marty Cagan.md",
                "followCursor": false,
                "showSearch": false,
                "searchQuery": ""
              },
              "icon": "lucide-list",
              "title": "Outline of 2024 - Transformed by Marty Cagan"
            }
          },
          {
            "id": "da11cc124ddd8e44",
            "type": "leaf",
            "state": {
              "type": "calendar",
              "state": {},
              "icon": "calendar-with-checkmark",
              "title": "Calendar"
            }
          },
          {
            "id": "aa6e22c7ac69cb25",
            "type": "leaf",
            "state": {
              "type": "git-view",
              "state": {},
              "icon": "git-pull-request",
              "title": "Source Control"
            }
          }
        ],
        "currentTab": 6
      }
    ],
    "direction": "horizontal",
    "width": 300
  },
  "left-ribbon": {
    "hiddenItems": {
      "switcher:Open quick switcher": false,
      "graph:Open graph view": false,
      "canvas:Create new canvas": false,
      "templates:Insert template": false,
      "command-palette:Open command palette": false,
      "bases:Create new base": false,
      "obsidian-git:Open Git source control": false,
      "templater-obsidian:Templater": false,
      "periodic-notes:Open today": false
    }
  },
  "active": "01bde706ddefb4c5",
  "lastOpenFiles": [
    "80 Back Office/Cosmos for Books.md",
    "40 Knowledge/10 Books/2024/2024 - Transformed by Marty Cagan.md",
    "40 Knowledge/10 Books/2024",
    "40 Knowledge/10 Books/2024.md",
    "40 Knowledge/10 Books/2025",
    "00 Inbox/Book Reviews/Mastering Git ~ Book Review.md",
    "10 Journal/Daily/26_01/05/26-01-05 Daily Notes.md",
    "40 Knowledge/10 Books",
    "10 Journal/Daily/26_01/05/26-01-05 Daily Me.md",
    "10 Journal/Daily/26_01/05/26-01-05 Daily Learn.md",
    "10 Journal/Daily/26_01/05/26-01-05 Daily Fit.md",
    "80 Back Office/Templates/Daily Notes Template.md",
    "10 Journal/Daily/26_01/05",
    "00 Inbox/Learn to Listen.md",
    "40 Knowledge/Scrum/Why We Replaced Daily Standups with Written Daily Logs.md",
    "00 Inbox/Untitled.md",
    "40 Knowledge/Scrum",
    "Uni Map Canvas.canvas",
    "00 Inbox/Untitled 2.md",
    "00 Inbox/Untitled 3.md",
    "00 Inbox/QNX Operating System.md",
    "Uni Map Canvas 1.canvas",
    "10 Journal/Daily/26_01/04/26-01-04 Daily Notes.md",
    "10 Journal/Daily/26_01/04/26-01-04 Daily Fit.md",
    "10 Journal/Daily/26_01/04/26-01-04 Daily Me.md",
    "10 Journal/Daily/26_01/04/26-01-04 Daily Learn.md",
    "00 Inbox/Go Programming Language.md",
    "10 Journal/Daily/26_01/04",
    "00 Inbox/Jenkins.md",
    "00 Inbox/Untitled.canvas",
    "00 Inbox/Untitled.base",
    "00 Inbox/Zig Programming Language.md",
    "00 Inbox/C++ Programming Language.md",
    "00 Inbox/Java Programming Language.md",
    "00 Inbox/Lua Programming Language.md",
    "00 Inbox/Perl Programming Language.md",
    "10 Journal/Daily/26_01/03",
    "90 Attachements/Pasted image 20260102123317.png",
    "90 Attachements/Pasted image 20260102121540.png",
    "99 Archives",
    "90 Attachements",
    "00 Inbox/Pasted image 20251229132703.png",
    "00 Inbox/Pasted image 20251229114546.png",
    "99 Attachments/Pasted image 20251229114546.png"
  ]
}